ssm/__init__.py
ssm/client.py
ssm/server.py
ssm_python-0.0.2.dist-info/METADATA
ssm_python-0.0.2.dist-info/WHEEL
ssm_python-0.0.2.dist-info/top_level.txt
ssm_python-0.0.2.dist-info/RECORD
