Metadata-Version: 2.1
Name: ssm-python
Version: 0.0.2
Summary: Simple Screen Mirror
Home-page: UNKNOWN
Author: JHLeeeMe
Author-email: lejung92@gmail.com
License: UNKNOWN
Project-URL: Source, https://github.com/JHLeeeMe/ssm
Keywords: python,socket,screen,mirroring,sharing,screen mirroring,screen sharing
Platform: UNKNOWN
Classifier: Programming Language :: Python :: 3.7
Classifier: Programming Language :: Python :: 3.8
Classifier: Programming Language :: Python :: 3.9
Classifier: License :: OSI Approved :: MIT License
Classifier: Operating System :: POSIX :: Linux
Requires-Python: >=3.7
Requires-Dist: opencv-python
Requires-Dist: Pillow
Requires-Dist: python-xlib
